h5pandas/__init__.py
h5pandas/dataframe.py
h5pandas/group.py
h5pandas/h5array.py
h5pandas/h5datatype.py
h5pandas-0.19.dist-info/licenses/LICENSE
h5pandas-0.19.dist-info/METADATA
h5pandas-0.19.dist-info/WHEEL
h5pandas-0.19.dist-info/top_level.txt
h5pandas-0.19.dist-info/RECORD
